causal_toolkit_mkhan/__init__.py
causal_toolkit_mkhan/meta_learners.py
causal_toolkit_mkhan/propensity.py
causal_toolkit_mkhan/rct.py
causal_toolkit_mkhan-0.1.1.dist-info/licenses/LICENSE
causal_toolkit_mkhan-0.1.1.dist-info/METADATA
causal_toolkit_mkhan-0.1.1.dist-info/WHEEL
causal_toolkit_mkhan-0.1.1.dist-info/top_level.txt
causal_toolkit_mkhan-0.1.1.dist-info/RECORD
