Metadata-Version: 2.4
Name: causal-toolkit-mkhan
Version: 0.1.1
Summary: A Python package for causal inference methods including RCT analysis, propensity score methods, and meta-learners.
Author-email: mkhan <mohammadokhan95@gmail.com>
License: MIT
Project-URL: Homepage, https://github.com/mokhan95/causal-toolkit-mkhan
Project-URL: Documentation, https://github.com/mokhan95/causal-toolkit-mkhan#readme
Project-URL: Repository, https://github.com/mokhan95/causal-toolkit-mkhan
Project-URL: Bug Tracker, https://github.com/mokhan95/causal-toolkit-mkhan/issues
Keywords: causal inference,statistics,machine learning,treatment effects
Classifier: Development Status :: 3 - Alpha
Classifier: Intended Audience :: Science/Research
Classifier: License :: OSI Approved :: MIT License
Classifier: Programming Language :: Python :: 3
Classifier: Programming Language :: Python :: 3.8
Classifier: Programming Language :: Python :: 3.9
Classifier: Programming Language :: Python :: 3.10
Classifier: Programming Language :: Python :: 3.11
Classifier: Topic :: Scientific/Engineering :: Mathematics
Classifier: Topic :: Scientific/Engineering :: Information Analysis
Requires-Python: >=3.8
License-File: LICENSE
Requires-Dist: pandas>=1.3.0
Requires-Dist: numpy>=1.21.0
Requires-Dist: scipy>=1.7.0
Requires-Dist: scikit-learn>=1.0.0
Requires-Dist: lightgbm>=3.3.0
Requires-Dist: patsy>=0.5.0
Requires-Dist: packaging>=20.0
Provides-Extra: dev
Requires-Dist: pytest>=7.0.0; extra == "dev"
Requires-Dist: pytest-cov>=3.0.0; extra == "dev"
Requires-Dist: black>=22.0.0; extra == "dev"
Requires-Dist: pylint>=2.12.0; extra == "dev"
Requires-Dist: mypy>=0.950; extra == "dev"
Dynamic: license-file
